jpvm/__init__.py
jpvm/compiler.py
jpvm/instr.py
jpvm/vm.py
jpvm-0.1.1.dist-info/METADATA
jpvm-0.1.1.dist-info/WHEEL
jpvm-0.1.1.dist-info/top_level.txt
jpvm-0.1.1.dist-info/RECORD
