Metadata-Version: 2.4
Name: jpvm
Version: 0.1.1
Summary: 日本語で書けるPython製ミニ仮想マシン
Author: kirby
Requires-Python: >=3.9
